deepimg3/__init__.py
deepimg3/__main__.py
deepimg3/get_images.py
deepimg3/resolution.py
example.env
LICENSE
promptsets.example.json
pyproject.toml
README.md
deepimg3-1.4.1.dist-info/LICENSE
deepimg3-1.4.1.dist-info/METADATA
deepimg3-1.4.1.dist-info/WHEEL
deepimg3-1.4.1.dist-info/RECORD
