Metadata-Version: 2.1
Name: deepimg3
Version: 1.4.1
Summary: Automated testing for the DeepAI text to image api
License: MIT
Author: DJ Magar
Author-email: dj@deepai.org
Requires-Python: >=3.12,<4.0
Classifier: License :: OSI Approved :: MIT License
Classifier: Programming Language :: Python :: 3
Classifier: Programming Language :: Python :: 3.12
Requires-Dist: httpx (>=0.27.0,<0.28.0)
Requires-Dist: tqdm (>=4.66.2,<5.0.0)
